ZtoRGBpy/__init__.py
ZtoRGBpy/_core.py
ZtoRGBpy/_info.py
ZtoRGBpy/_mpl.py
ZtoRGBpy-1.0.1.dist-info/LICENSE
ZtoRGBpy-1.0.1.dist-info/METADATA
ZtoRGBpy-1.0.1.dist-info/WHEEL
ZtoRGBpy-1.0.1.dist-info/top_level.txt
ZtoRGBpy-1.0.1.dist-info/zip-safe
ZtoRGBpy-1.0.1.dist-info/RECORD
