Metadata-Version: 2.1
Name: ZtoRGBpy
Version: 1.0.1
Summary: Complex number to perceptually uniform RGB subset mapping library
Home-page: https://ztorgbpy.glenfletcher.com/
Author: Glen Fletcher
Author-email: mail@glenfletcher.com
License: Apache License, Version 2.0
Project-URL: Bug Tracker, https://github.com/glenfletcher/ztorgbpy/issues
Project-URL: Source Code, https://github.com/glenfletcher/ztorgbpy
Platform: UNKNOWN
Classifier: Development Status :: 5 - Production/Stable
Classifier: Intended Audience :: Science/Research
Classifier: Natural Language :: English
Classifier: License :: OSI Approved
Classifier: Operating System :: OS Independent
Classifier: Programming Language :: Python :: 3
Classifier: Programming Language :: Python :: 3.5
Classifier: Programming Language :: Python :: 3.6
Classifier: Programming Language :: Python :: 3.7
Classifier: Topic :: Scientific/Engineering :: Visualization
Classifier: Topic :: Scientific/Engineering :: Mathematics
Classifier: Topic :: Scientific/Engineering :: Physics
Requires-Dist: numpy (<2,>=1.6)
Provides-Extra: plot
Requires-Dist: matplotlib (<3,>=1.3) ; extra == 'plot'
